tinytorchutil/__init__.py
tinytorchutil/tinytorchutil.py
tinytorchutil-0.1.3.dist-info/METADATA
tinytorchutil-0.1.3.dist-info/WHEEL
tinytorchutil-0.1.3.dist-info/top_level.txt
tinytorchutil-0.1.3.dist-info/RECORD
