Metadata-Version: 2.1
Name: tinytorchutil
Version: 0.1.3
Summary: A personal collection of small utility functions for PyTorch and DL development.
Author: Chainathan
Requires-Python: >=3.6
Requires-Dist: torch
Requires-Dist: matplotlib
Requires-Dist: numpy
Requires-Dist: fastcore
Requires-Dist: fastprogress
Requires-Dist: torcheval
Requires-Dist: wandb
